hdl/FIFOlogic.v
`timescale 100ps / 1ps

module FIFOLOGIC (
   input clk,
   input FFA,
   input RXF,
   input TXE,
   input EFB,
   output reg D1,
   output reg D2
);

assign #28 FFA_N = FFA;
assign #28 EFB_N = ~EFB;

assign #28 x1 = RXF | FFA_N;
assign #28 x2 = TXE | EFB_N;

assign #29 x3 = x1 & x2;
assign #28 x1_n = ~x1;

assign #28 d1 = x3 | x1_n;
assign #28 d2 = x1 | x3;

always@(posedge clk) begin
   D1 <= d1;
   D2 <= d2;
end

endmodule

simulation/testbench/TB_fifologic.v
`timescale 100ps/ 1ps
`define timeperiodby2 50

module tb_FIFOLOGIC;

reg clk;
reg FFA, EFB, RXF, TXE;
wire D1, D2;

FIFOLOGIC uut
(
   .clk(clk),
   .FFA(FFA),
   .RXF(RXF),
   .TXE(TXE),
   .EFB(EFB),
   .D1(D1),
   .D2(D2)
);

initial begin
   $dumpfile("wave.vcd");
   $dumpvars(0,tb_FIFOLOGIC);
end
 
initial begin
   clk = 0;
   FFA = 1'b0; EFB = 1'b0; RXF = 1'b0; TXE = 1'b0;
   #10
   $display("\nSimulation Started...");
  
	{FFA,EFB,RXF,TXE} = 4'b0000;
   #50  
	{FFA,EFB,RXF,TXE} = 4'b1001;
   #50
	{FFA,EFB,RXF,TXE} = 4'b0000;
   #50  
	{FFA,EFB,RXF,TXE} = 4'b0000;
   #50  
	{FFA,EFB,RXF,TXE} = 4'b0000;
   #50

   #1000
   $display("\nSimulation Finished");
   $finish;
end
              
always
   #`timeperiodby2 clk = ~clk;

endmodule

simulation/wave.vcd
$date
	Thu Jun 25 12:31:41 2015
$end
$version
	Icarus Verilog
$end
$timescale
	1ps
$end
$scope module tb_FIFOLOGIC $end
$var wire 1 ! D1 $end
$var wire 1 " D2 $end
$var reg 1 # EFB $end
$var reg 1 $ FFA $end
$var reg 1 % RXF $end
$var reg 1 & TXE $end
$var reg 1 ' clk $end
$scope module uut $end
$var wire 1 ( EFB $end
$var wire 1 ) EFB_N $end
$var wire 1 * FFA $end
$var wire 1 + FFA_N $end
$var wire 1 , RXF $end
$var wire 1 - TXE $end
$var wire 1 . clk $end
$var wire 1 / d1 $end
$var wire 1 0 d2 $end
$var wire 1 1 x1 $end
$var wire 1 2 x1_n $end
$var wire 1 3 x2 $end
$var wire 1 4 x3 $end
$var reg 1 5 D1 $end
$var reg 1 6 D2 $end
$upscope $end
$upscope $end
$enddefinitions $end
#0
$dumpvars
x6
x5
x4
x3
x2
x1
x0
x/
0.
0-
0,
x+
0*
z)
0(
0'
0&
0%
0$
0#
x"
x!
$end
#2800
1)
0+
#5000
1'
1.
#5600
13
01
#6000
1$
1*
1&
1-
#8400
12
#8500
04
#8800
1+
#10000
0'
0.
#11000
0$
0*
0&
0-
#11200
1/
#11300
00
#11600
11
#13800
0+
#14400
02
10
#14500
14
#15000
16
1"
15
1!
1'
1.
#16600
01
#19400
12
#19500
04
#20000
0'
0.
#22300
00
#25000
06
0"
1'
1.
